httpproblem/__init__.py
httpproblem/problem.py
httpproblem-0.2.0.dist-info/DESCRIPTION.rst
httpproblem-0.2.0.dist-info/METADATA
httpproblem-0.2.0.dist-info/RECORD
httpproblem-0.2.0.dist-info/WHEEL
httpproblem-0.2.0.dist-info/metadata.json
httpproblem-0.2.0.dist-info/top_level.txt
