Metadata-Version: 2.0
Name: httpproblem
Version: 0.2.0
Summary: Utility library to work with RFC7807 Problem Details for HTTP APIs
Home-page: https://github.com/cbornet/python-httpproblem
Author: Christophe Bornet
Author-email: cbornet@hotmail.com
License: MIT
Download-URL: https://pypi.python.org/pypi/httpproblem
Keywords: rfc7807 problem http json
Platform: any
